RitalinCoder/src/RitalinCoder/__init__.py
RitalinCoder/src/RitalinCoder/main.py
ritalincoder-1.0.0.dist-info/licenses/LICENSE
ritalincoder-1.0.0.dist-info/METADATA
ritalincoder-1.0.0.dist-info/WHEEL
ritalincoder-1.0.0.dist-info/entry_points.txt
ritalincoder-1.0.0.dist-info/top_level.txt
ritalincoder-1.0.0.dist-info/RECORD
