Metadata-Version: 2.4
Name: RitalinCoder
Version: 1.0.0
Summary: Telegram based remote access tool
Author-email: RitalinCoder <rootritalin@gmail.com>
License: MIT
Project-URL: Homepage, https://github.com/RootRitalin/RitalinCoder
Project-URL: Bug Reports, https://github.com/RootRitalin/RitalinCoder/issues
Keywords: telegram,remote,access,tool
Classifier: Development Status :: 4 - Beta
Classifier: Intended Audience :: Developers
Classifier: License :: OSI Approved :: MIT License
Classifier: Operating System :: OS Independent
Classifier: Programming Language :: Python :: 3
Classifier: Programming Language :: Python :: 3.7
Classifier: Programming Language :: Python :: 3.8
Classifier: Programming Language :: Python :: 3.9
Classifier: Programming Language :: Python :: 3.10
Classifier: Programming Language :: Python :: 3.11
Requires-Python: >=3.7
License-File: LICENSE
Requires-Dist: pyTelegramBotAPI>=4.14.0
Dynamic: license-file
